README.md
setup.py
src/kali/__init__.py
src/kali/forms.py
src/kali/implementation.py
src/kali/version.py
src/kali.egg-info/PKG-INFO
src/kali.egg-info/SOURCES.txt
src/kali.egg-info/dependency_links.txt
src/kali.egg-info/top_level.txt