Metadata-Version: 2.1
Name: kali
Version: 0.0.7
Summary: Simple, reliable, single-threaded HTTP service in Python. Aimed at serving web application to localhost as alternative to desktop application development.
Home-page: https://github.com/kjosib/kali
Author: Ian Kjos
Author-email: kjosib@gmail.com
License: UNKNOWN
Platform: UNKNOWN
Classifier: Programming Language :: Python :: 3.7
Classifier: License :: OSI Approved :: MIT License
Classifier: Operating System :: OS Independent
Classifier: Intended Audience :: Developers
Classifier: Development Status :: 3 - Alpha
Classifier: Environment :: Console
Classifier: Environment :: No Input/Output (Daemon)
Classifier: Environment :: Web Environment
Classifier: Topic :: Internet :: WWW/HTTP :: HTTP Servers
